yodlee/__init__.py
yodlee/client.py
yodlee/cobrand.py
yodlee/config.py
yodlee/error.py
yodlee/user.py
yodlee-0.1.6.dist-info/DESCRIPTION.rst
yodlee-0.1.6.dist-info/METADATA
yodlee-0.1.6.dist-info/RECORD
yodlee-0.1.6.dist-info/WHEEL
yodlee-0.1.6.dist-info/metadata.json
yodlee-0.1.6.dist-info/top_level.txt
