Metadata-Version: 2.0
Name: yodlee
Version: 0.1.6
Summary: Envestnet Yodlee API Client
Home-page: https://github.com/cogolabs/yodlee
Author: Ben Feeser
Author-email: bfeeser@cogolabs.com
License: Apache 2.0
Keywords: envestnet yodlee fintech account aggregation
Platform: UNKNOWN
Classifier: Development Status :: 4 - Beta
Classifier: Intended Audience :: Developers
Classifier: Topic :: Software Development :: Libraries :: Python Modules
Classifier: License :: OSI Approved :: Apache Software License
Classifier: Programming Language :: Python :: 2
Classifier: Programming Language :: Python :: 2.7
Classifier: Programming Language :: Python :: 3
Classifier: Programming Language :: Python :: 3.3
Classifier: Programming Language :: Python :: 3.4
Classifier: Programming Language :: Python :: 3.5
Classifier: Programming Language :: Python :: 3.6
Requires-Dist: requests
